stash-0.3.0.dist-info/METADATA
stash-0.3.0.dist-info/WHEEL
stash/__init__.py
stash/stash.pyd
stash-0.3.0.dist-info/RECORD
