Metadata-Version: 2.4
Name: stash
Version: 0.3.0
